README.md
setup.py
accusort.egg-info/PKG-INFO
accusort.egg-info/SOURCES.txt
accusort.egg-info/dependency_links.txt
accusort.egg-info/entry_points.txt
accusort.egg-info/requires.txt
accusort.egg-info/top_level.txt
eagle/__init__.py
eagle/main.py
eagle/scripts/__init__.py
eagle/scripts/banner.txt
eagle/scripts/document_reader.py
eagle/scripts/pl_art.py