Metadata-Version: 2.1
Name: accusort
Version: 0.3
Summary: AccuSort
Home-page: UNKNOWN
Author: Sixtysix Technologies
Author-email: sangeeth@sixtysixtech.com
License: UNKNOWN
Platform: UNKNOWN
